tryton_filestore_gs.py
tryton_filestore_gs-0.2.0.dist-info/LICENSE
tryton_filestore_gs-0.2.0.dist-info/METADATA
tryton_filestore_gs-0.2.0.dist-info/WHEEL
tryton_filestore_gs-0.2.0.dist-info/top_level.txt
tryton_filestore_gs-0.2.0.dist-info/RECORD
