Metadata-Version: 2.1
Name: tryton-filestore-gs
Version: 0.2.0
Summary: Store Tryton files on Google Cloud Storage
Home-page: https://hg.b2ck.com/tryton-filestore-gs
Author: B2CK
Author-email: info@b2ck.com
License: GPL-3
Keywords: tryton google cloud storage
Platform: Posix; MacOS X; Windows
Classifier: Framework :: Tryton
Classifier: Intended Audience :: Developers
Classifier: License :: OSI Approved :: GNU General Public License (GPL)
Classifier: Operating System :: OS Independent
Classifier: Programming Language :: Python :: 2
Classifier: Programming Language :: Python :: 2.7
Classifier: Programming Language :: Python :: 3
Classifier: Programming Language :: Python :: 3.4
Classifier: Programming Language :: Python :: 3.5
Classifier: Programming Language :: Python :: 3.6
Classifier: Topic :: Internet
Requires-Dist: google-cloud-storage
Requires-Dist: trytond (>4.2)
